zekai_utils/__init__.py
zekai_utils-0.0.0.dist-info/METADATA
zekai_utils-0.0.0.dist-info/WHEEL
zekai_utils-0.0.0.dist-info/top_level.txt
zekai_utils-0.0.0.dist-info/RECORD
